Workbook
Name Slicer_Category: #N/A
Name Slicer_Segment: #N/A
Name Slicer_Ship_Mode: #N/A
Name Slicer_State: #N/A

Sheet FILTER
A1: Order ID | B1: Ship Mode | C1: Customer Name | D1: Segment | E1: State | F1: Postal Code | G1: Category | H1: Cost of Goods | I1: Price | J1: Quantity | K1: MOBILE | L1: Order ID | M1: Ship Mode | N1: Customer Name | O1: Segment | P1: State | Q1: Postal Code | R1: Category | S1: Cost of Goods | T1: Price | U1: Quantity
A2: US-2017-108063 | B2: First Class | C2: Adam Shillingsburg | D2: Consumer | E2: Virginia | F2: 22901 | G2: Laptop | H2: 24.255 | I2: 34.65 | J2: 3 | K2: =_xlfn.FORMULATEXT(L2) -> =FILTER(A2:J60,G2:G60=K1,"NO DATA") | L2: {=_xlfn._xlws.FILTER(A2:J60,G2:G60=K1,"NO DATA")} -> CA-2017-126788 | M2: First Class | N2: Adrian Barton | O2: Consumer | P2: Texas | Q2: 77581 | R2: Mobile | S2: 329.2632 | T2: 470.376 | U2: 3
A3: CA-2014-152905 | B3: Standard Class | C3: Aaron Bergman | D3: Consumer | E3: Texas | F3: 76017 | G3: Laptop | H3: 8.8368 | I3: 12.624 | J3: 2 | L3: CA-2017-136448 | M3: First Class | N3: Adam Shillingsburg | O3: Consumer | P3: Pennsylvania | Q3: 19143 | R3: Mobile | S3: 50.3832 | T3: 71.976 | U3: 3
A4: CA-2016-104311 | B4: Standard Class | C4: Adam Shillingsburg | D4: Consumer | E4: Texas | F4: 75061 | G4: Laptop | H4: 13.2552 | I4: 18.936 | J4: 3 | L4: CA-2017-121643 | M4: First Class | N4: Adrian Barton | O4: Consumer | P4: Oregon | Q4: 97206 | R4: Mobile | S4: 241.2928 | T4: 344.704 | U4: 2
A5: CA-2015-163181 | B5: Standard Class | C5: Adrian Barton | D5: Consumer | E5: Texas | F5: 77041 | G5: Laptop | H5: 16.548 | I5: 23.64 | J5: 3 | L5: CA-2016-140935 | M5: First Class | N5: Aaron Bergman | O5: Consumer | P5: Oklahoma | Q5: 73120 | R5: Mobile | S5: 155.386 | T5: 221.98 | U5: 2
A6: CA-2016-119865 | B6: Standard Class | C6: Adam Shillingsburg | D6: Consumer | E6: New York | F6: 10011 | G6: Laptop | H6: 25.592 | I6: 36.56 | J6: 5 | L6: CA-2017-140781 | M6: Standard Class | N6: Adrian Barton | O6: Consumer | P6: Illinois | Q6: 61701 | R6: Mobile | S6: 27.8712 | T6: 39.816 | U6: 3
A7: CA-2016-147431 | B7: Standard Class | C7: Adrian Barton | D7: Consumer | E7: New York | F7: 10011 | G7: Laptop | H7: 82.572 | I7: 117.96 | J7: 2 | L7: CA-2017-162691 | M7: Standard Class | N7: Aaron Smayling | O7: Corporate | P7: Texas | Q7: 78745 | R7: Mobile | S7: 1007.9874 | T7: 1439.982 | U7: 3
A8: CA-2017-145877 | B8: Second Class | C8: Adam Shillingsburg | D8: Consumer | E8: Missouri | F8: 65807 | G8: Laptop | H8: 65.94 | I8: 94.2 | J8: 6 | L8: CA-2017-113481 | M8: First Class | N8: Aaron Smayling | O8: Corporate | P8: North Carolina | Q8: 28540 | R8: Mobile | S8: 486.99 | T8: 695.7 | U8: 2
A9: CA-2015-127509 | B9: Standard Class | C9: Adam Shillingsburg | D9: Consumer | E9: Missouri | F9: 65807 | G9: Laptop | H9: 12.054 | I9: 17.22 | J9: 3 | L9: CA-2014-157644 | M9: First Class | N9: Aaron Hawkins | O9: Corporate | P9: New York | Q9: 10035 | R9: Mobile | S9: 24.339 | T9: 34.77 | U9: 3
A10: CA-2016-117121 | B10: Standard Class | C10: Adrian Barton | D10: Consumer | E10: Michigan | F10: 48205 | G10: Laptop | H10: 6924.918 | I10: 9892.74 | J10: 13 | L10: CA-2016-129714 | M10: First Class | N10: Adam Bellavance | O10: Home Office | P10: New York | Q10: 10009 | R10: Mobile | S10: 4.753 | T10: 6.79 | U10: 1
A11: CA-2014-103100 | B11: First Class | C11: Adrian Barton | D11: Consumer | E11: Indiana | F11: 46203 | G11: Laptop | H11: 2.583 | I11: 3.69 | J11: 1 | L11: CA-2016-135594 | M11: Second Class | N11: Adrian Hane | O11: Home Office | P11: Illinois | Q11: 60505 | R11: Mobile | S11: 35.084 | T11: 50.12 | U11: 7
A12: CA-2016-150007 | B12: Standard Class | C12: Adam Shillingsburg | D12: Consumer | E12: Illinois | F12: 60653 | G12: Laptop | H12: 4.2 | I12: 6 | J12: 2 | L12: CA-2017-159688 | M12: Standard Class | N12: Adam Bellavance | O12: Home Office | P12: California | Q12: 90004 | R12: Mobile | S12: 55.993 | T12: 79.99 | U12: 1
A13: CA-2014-132913 | B13: First Class | C13: Adam Shillingsburg | D13: Consumer | E13: California | F13: 92037 | G13: Laptop | H13: 9.779 | I13: 13.97 | J13: 1
A14: CA-2017-153822 | B14: Standard Class | C14: Adrian Barton | D14: Consumer | E14: Arizona | F14: 85023 | G14: Laptop | H14: 8.8368 | I14: 12.624 | J14: 2
A15: CA-2017-126788 | B15: First Class | C15: Adrian Barton | D15: Consumer | E15: Texas | F15: 77581 | G15: Mobile | H15: 329.2632 | I15: 470.376 | J15: 3
A16: CA-2017-136448 | B16: First Class | C16: Adam Shillingsburg | D16: Consumer | E16: Pennsylvania | F16: 19143 | G16: Mobile | H16: 50.3832 | I16: 71.976 | J16: 3
A17: CA-2017-121643 | B17: First Class | C17: Adrian Barton | D17: Consumer | E17: Oregon | F17: 97206 | G17: Mobile | H17: 241.2928 | I17: 344.704 | J17: 2
A18: CA-2016-140935 | B18: First Class | C18: Aaron Bergman | D18: Consumer | E18: Oklahoma | F18: 73120 | G18: Mobile | H18: 155.386 | I18: 221.98 | J18: 2
A19: CA-2017-140781 | B19: Standard Class | C19: Adrian Barton | D19: Consumer | E19: Illinois | F19: 61701 | G19: Mobile | H19: 27.8712 | I19: 39.816 | J19: 3
A20: CA-2014-156587 | B20: First Class | C20: Aaron Bergman | D20: Consumer | E20: Washington | F20: 98103 | G20: TV | H20: 34.0984 | I20: 48.712 | J20: 1
A21: CA-2014-156160 | B21: Standard Class | C21: Adam Shillingsburg | D21: Consumer | E21: New York | F21: 10035 | G21: TV | H21: 68.208 | I21: 97.44 | J21: 3
A22: CA-2017-101042 | B22: Standard Class | C22: Adrian Barton | D22: Consumer | E22: Kentucky | F22: 42420 | G22: TV | H22: 575.316 | I22: 821.88 | J22: 6
A23: US-2016-122245 | B23: Standard Class | C23: Adrian Barton | D23: Consumer | E23: Arizona | F23: 85023 | G23: TV | H23: 275.2155 | I23: 393.165 | J23: 3
A24: CA-2016-162901 | B24: First Class | C24: Aaron Smayling | D24: Corporate | E24: Virginia | F24: 22204 | G24: Laptop | H24: 21.98 | I24: 31.4 | J24: 2
... A60: CA-2014-123295 | B60: Same Day | C60: Adrian Hane | D60: Home Office | E60: Arizona | F60: 85705 | G60: TV | H60: 181.3952 | I60: 259.136 | J60: 4

Sheet LOOKUP
A1: Order ID | B1: Ship Mode | C1: Customer Name | D1: Segment | E1: State | F1: Postal Code | G1: Category | H1: Cost of Goods | I1: Price | J1: Quantity | L1: Price
A2: US-2017-108063 | B2: First Class | C2: Adam Shillingsburg | D2: Consumer | E2: Virginia | F2: 22901 | G2: Laptop | H2: 24.255 | I2: 34.65 | J2: 3 | L2: =MATCH(L1,A1:J1,0) -> 9 | M2: =_xlfn.FORMULATEXT(L2) -> =MATCH(L1,A1:J1,0)
A3: CA-2014-103100 | B3: First Class | C3: Adrian Barton | D3: Consumer | E3: Indiana | F3: 46203 | G3: Laptop | H3: 2.583 | I3: 3.69 | J3: 1 | S3: PRICE | T3: 500
A4: CA-2014-132913 | B4: First Class | C4: Adam Shillingsburg | D4: Consumer | E4: California | F4: 92037 | G4: Laptop | H4: 9.779 | I4: 13.97 | J4: 1
A5: CA-2016-162901 | B5: First Class | C5: Aaron Smayling | D5: Corporate | E5: Virginia | F5: 22204 | G5: Laptop | H5: 21.98 | I5: 31.4 | J5: 2 | L5: Order ID | M5: Ship Mode | N5: Customer Name | O5: Segment | Q5: NAME | R5: QUANTITY | S5: TOTAL PRICE
A6: CA-2017-112004 | B6: First Class | C6: Adam Hart | D6: Corporate | E6: Pennsylvania | F6: 19013 | G6: Laptop | H6: 6.0165 | I6: 8.595 | J6: 5 | L6: CA-2014-156587 | M6: =VLOOKUP(L6,A:B,2,0) -> First Class | N6: =VLOOKUP(L6,A:C,3,0) -> Aaron Bergman | O6: =VLOOKUP(L6,A:J,4,0) -> Consumer | Q6: A | R6: 5 | S6: =R6*$T$3 -> 2500
A7: US-2017-147655 | B7: First Class | C7: Aaron Smayling | D7: Corporate | E7: Oregon | F7: 97756 | G7: Laptop | H7: 61.6518 | I7: 88.074 | J7: 7 | L7: CA-2017-125451 | M7: =VLOOKUP(L7,A:B,2,0) -> First Class | N7: =VLOOKUP(L7,A:C,3,0) -> Adam Hart | O7: =VLOOKUP(L7,A:J,4,0) -> Corporate | Q7: B | R7: 3 | S7: =R7*$T$3 -> 1500
A8: US-2014-158400 | B8: First Class | C8: Aaron Hawkins | D8: Corporate | E8: California | F8: 94109 | G8: Laptop | H8: 34.5856 | I8: 49.408 | J8: 4 | L8: CA-2017-118857 | M8: =VLOOKUP(L8,A:B,2,0) -> First Class | N8: =VLOOKUP(L8,A:C,3,0) -> Adam Hart | O8: =VLOOKUP(L8,A:J,4,0) -> Corporate | Q8: C | R8: 7 | S8: =R8*$T$3 -> 3500
A9: CA-2016-145261 | B9: First Class | C9: Adrian Hane | D9: Home Office | E9: Oregon | F9: 97301 | G9: Laptop | H9: 31.668 | I9: 45.24 | J9: 4 | L9: CA-2016-148747 | M9: =VLOOKUP(L9,A:B,2,0) -> First Class | N9: =VLOOKUP(L9,A:C,3,0) -> Aaron Smayling | O9: =VLOOKUP(L9,A:J,4,0) -> Corporate | Q9: D | R9: 9 | S9: =R9*$T$3 -> 4500
A10: CA-2017-118213 | B10: First Class | C10: Adam Bellavance | D10: Home Office | E10: Indiana | F10: 46142 | G10: Laptop | H10: 3.087 | I10: 4.41 | J10: 1 | L10: CA-2016-144015 | M10: =VLOOKUP(L10,A:B,2,0) -> Same Day | N10: =VLOOKUP(L10,A:C,3,0) -> Adam Hart | O10: =VLOOKUP(L10,A:J,4,0) -> Corporate
A11: CA-2017-126788 | B11: First Class | C11: Adrian Barton | D11: Consumer | E11: Texas | F11: 77581 | G11: Mobile | H11: 329.2632 | I11: 470.376 | J11: 3 | L11: CA-2014-123295 | M11: =VLOOKUP(L11,A:B,2,0) -> Same Day | N11: =VLOOKUP(L11,A:C,3,0) -> Adrian Hane | O11: =VLOOKUP(L11,A:J,4,0) -> Home Office
A12: CA-2017-136448 | B12: First Class | C12: Adam Shillingsburg | D12: Consumer | E12: Pennsylvania | F12: 19143 | G12: Mobile | H12: 50.3832 | I12: 71.976 | J12: 3 | L12: CA-2017-145877 | M12: =VLOOKUP(L12,A:B,2,0) -> Second Class | N12: =VLOOKUP(L12,A:C,3,0) -> Adam Shillingsburg | O12: =VLOOKUP(L12,A:J,4,0) -> Consumer
A13: CA-2017-121643 | B13: First Class | C13: Adrian Barton | D13: Consumer | E13: Oregon | F13: 97206 | G13: Mobile | H13: 241.2928 | I13: 344.704 | J13: 2 | L13: CA-2015-161795 | M13: =VLOOKUP(L13,A:B,2,0) -> Second Class | N13: =VLOOKUP(L13,A:C,3,0) -> Adam Hart | O13: =VLOOKUP(L13,A:J,4,0) -> Corporate
A14: CA-2016-140935 | B14: First Class | C14: Aaron Bergman | D14: Consumer | E14: Oklahoma | F14: 73120 | G14: Mobile | H14: 155.386 | I14: 221.98 | J14: 2 | L14: CA-2014-122070 | M14: =VLOOKUP(L14,A:B,2,0) -> Second Class | N14: =VLOOKUP(L14,A:C,3,0) -> Aaron Hawkins | O14: =VLOOKUP(L14,A:J,4,0) -> Corporate
A15: CA-2017-113481 | B15: First Class | C15: Aaron Smayling | D15: Corporate | E15: North Carolina | F15: 28540 | G15: Mobile | H15: 486.99 | I15: 695.7 | J15: 2 | L15: CA-2016-135594 | M15: =VLOOKUP(L15,A:B,2,0) -> Second Class | N15: =VLOOKUP(L15,A:C,3,0) -> Adrian Hane | O15: =VLOOKUP(L15,A:J,4,0) -> Home Office
A16: CA-2014-157644 | B16: First Class | C16: Aaron Hawkins | D16: Corporate | E16: New York | F16: 10035 | G16: Mobile | H16: 24.339 | I16: 34.77 | J16: 3
A17: CA-2016-129714 | B17: First Class | C17: Adam Bellavance | D17: Home Office | E17: New York | F17: 10009 | G17: Mobile | H17: 4.753 | I17: 6.79 | J17: 1 | L17: Order ID | M17: Ship Mode | N17: Customer Name | O17: Segment
A18: CA-2014-156587 | B18: First Class | C18: Aaron Bergman | D18: Consumer | E18: Washington | F18: 98103 | G18: TV | H18: 34.0984 | I18: 48.712 | J18: 1 | L18: CA-2014-156587 | M18: {=VLOOKUP(L18,A:J,{2,3,4},0)} -> First Class | N18: Aaron Bergman | O18: Consumer | Q18: =_xlfn.FORMULATEXT(M18) -> =VLOOKUP(L18,A:J,{2,3,4},0)
A19: CA-2017-125451 | B19: First Class | C19: Adam Hart | D19: Corporate | E19: Rhode Island | F19: 2920 | G19: TV | H19: 168.5208 | I19: 240.744 | J19: 4 | L19: CA-2017-125451 | M19: {=VLOOKUP(L19,A:J,{2,3,4},0)} -> First Class | N19: Adam Hart | O19: Corporate
A20: CA-2017-118857 | B20: First Class | C20: Adam Hart | D20: Corporate | E20: Nevada | F20: 89015 | G20: TV | H20: 137.515 | I20: 196.45 | J20: 5 | L20: CA-2017-118857 | M20: {=VLOOKUP(L20,A:J,{2,3,4},0)} -> First Class | N20: Adam Hart | O20: Corporate
A21: CA-2016-148747 | B21: First Class | C21: Aaron Smayling | D21: Corporate | E21: California | F21: 94110 | G21: TV | H21: 334.3662 | I21: 477.666 | J21: 2 | L21: CA-2016-148747 | M21: {=VLOOKUP(L21,A:J,{2,3,4},0)} -> First Class | N21: Aaron Smayling | O21: Corporate
A22: CA-2016-144015 | B22: Same Day | C22: Adam Hart | D22: Corporate | E22: California | F22: 90036 | G22: Laptop | H22: 162.204 | I22: 231.72 | J22: 2 | L22: CA-2016-144015 | M22: {=VLOOKUP(L22,A:J,{2,3,4},0)} -> Same Day | N22: Adam Hart | O22: Corporate
A23: CA-2014-123295 | B23: Same Day | C23: Adrian Hane | D23: Home Office | E23: Arizona | F23: 85705 | G23: TV | H23: 181.3952 | I23: 259.136 | J23: 4 | L23: CA-2014-123295 | M23: {=VLOOKUP(L23,A:J,{2,3,4},0)} -> Same Day | N23: Adrian Hane | O23: Home Office
A24: CA-2017-145877 | B24: Second Class | C24: Adam Shillingsburg | D24: Consumer | E24: Missouri | F24: 65807 | G24: Laptop | H24: 65.94 | I24: 94.2 | J24: 6 | L24: CA-2017-145877 | M24: {=VLOOKUP(L24,A:J,{2,3,4},0)} -> Second Class | N24: Adam Shillingsburg | O24: Consumer
A25: CA-2015-161795 | B25: Second Class | C25: Adam Hart | D25: Corporate | E25: Ohio | F25: 43229 | G25: Laptop | H25: 2.1056 | I25: 3.008 | J25: 2 | L25: CA-2015-161795 | M25: {=VLOOKUP(L25,A:J,{2,3,4},0)} -> Second Class | N25: Adam Hart | O25: Corporate
A26: CA-2014-122070 | B26: Second Class | C26: Aaron Hawkins | D26: Corporate | E26: New York | F26: 12180 | G26: Laptop | H26: 173.488 | I26: 247.84 | J26: 8 | L26: CA-2014-122070 | M26: {=VLOOKUP(L26,A:J,{2,3,4},0)} -> Second Class | N26: Aaron Hawkins | O26: Corporate
A27: CA-2016-135594 | B27: Second Class | C27: Adrian Hane | D27: Home Office | E27: Illinois | F27: 60505 | G27: Mobile | H27: 35.084 | I27: 50.12 | J27: 7 | L27: CA-2016-135594 | M27: {=VLOOKUP(L27,A:J,{2,3,4},0)} -> Second Class | N27: Adrian Hane | O27: Home Office
A28: CA-2017-145702 | B28: Second Class | C28: Adam Hart | D28: Corporate | E28: Tennessee | F28: 37918 | G28: TV | H28: 220.0464 | I28: 314.352 | J28: 3
A29: CA-2016-162747 | B29: Second Class | C29: Aaron Hawkins | D29: Corporate | E29: Mississippi | F29: 39503 | G29: TV | H29: 60.515 | I29: 86.45 | J29: 7
A30: CA-2014-152905 | B30: Standard Class | C30: Aaron Bergman | D30: Consumer | E30: Texas | F30: 76017 | G30: Laptop | H30: 8.8368 | I30: 12.624 | J30: 2
A31: CA-2016-104311 | B31: Standard Class | C31: Adam Shillingsburg | D31: Consumer | E31: Texas | F31: 75061 | G31: Laptop | H31: 13.2552 | I31: 18.936 | J31: 3
A32: CA-2015-163181 | B32: Standard Class | C32: Adrian Barton | D32: Consumer | E32: Texas | F32: 77041 | G32: Laptop | H32: 16.548 | I32: 23.64 | J32: 3
A33: CA-2016-119865 | B33: Standard Class | C33: Adam Shillingsburg | D33: Consumer | E33: New York | F33: 10011 | G33: Laptop | H33: 25.592 | I33: 36.56 | J33: 5
A34: CA-2016-147431 | B34: Standard Class | C34: Adrian Barton | D34: Consumer | E34: New York | F34: 10011 | G34: Laptop | H34: 82.572 | I34: 117.96 | J34: 2
A35: CA-2015-127509 | B35: Standard Class | C35: Adam Shillingsburg | D35: Consumer | E35: Missouri | F35: 65807 | G35: Laptop | H35: 12.054 | I35: 17.22 | J35: 3
A36: CA-2016-117121 | B36: Standard Class | C36: Adrian Barton | D36: Consumer | E36: Michigan | F36: 48205 | G36: Laptop | H36: 6924.918 | I36: 9892.74 | J36: 13
A37: CA-2016-150007 | B37: Standard Class | C37: Adam Shillingsburg | D37: Consumer | E37: Illinois | F37: 60653 | G37: Laptop | H37: 4.2 | I37: 6 | J37: 2
A38: CA-2017-153822 | B38: Standard Class | C38: Adrian Barton | D38: Consumer | E38: Arizona | F38: 85023 | G38: Laptop | H38: 8.8368 | I38: 12.624 | J38: 2
A39: CA-2016-147109 | B39: Standard Class | C39: Adam Hart | D39: Corporate | E39: Texas | F39: 76017 | G39: Laptop | H39: 36.288 | I39: 51.84 | J39: 10
... A60: US-2016-108637 | B60: Standard Class | C60: Adam Bellavance | D60: Home Office | E60: Virginia | F60: 22980 | G60: TV | H60: 89.516 | I60: 127.88 | J60: 2

Sheet Raw_data
A1: Order ID | B1: Ship Mode | C1: Customer Name | D1: Segment | E1: State | F1: Postal Code | G1: Category | H1: Cost of Goods | I1: Price | J1: Quantity | K1: Sales | L1: Profit | M1: Profit Margin
A2: US-2017-108063 | B2: First Class | C2: Adam Shillingsburg | D2: Consumer | E2: Virginia | F2: 22901 | G2: Laptop | H2: 24.255 | I2: 34.65 | J2: 3 | K2: =I2*J2 -> 103.95 | L2: =J2*(I2-H2) -> 31.185 | M2: =L2/K2 -> 0.3
A3: CA-2014-103100 | B3: First Class | C3: Adrian Barton | D3: Consumer | E3: Indiana | F3: 46203 | G3: Laptop | H3: 2.583 | I3: 3.69 | J3: 1 | K3: =I3*J3 -> 3.69 | L3: =J3*(I3-H3) -> 1.107 | M3: =L3/K3 -> 0.3
A4: CA-2014-132913 | B4: First Class | C4: Adam Shillingsburg | D4: Consumer | E4: California | F4: 92037 | G4: Laptop | H4: 9.779 | I4: 13.97 | J4: 1 | K4: =I4*J4 -> 13.97 | L4: =J4*(I4-H4) -> 4.191 | M4: =L4/K4 -> 0.3
A5: CA-2016-162901 | B5: First Class | C5: Aaron Smayling | D5: Corporate | E5: Virginia | F5: 22204 | G5: Laptop | H5: 21.98 | I5: 31.4 | J5: 2 | K5: =I5*J5 -> 62.8 | L5: =J5*(I5-H5) -> 18.84 | M5: =L5/K5 -> 0.3
A6: CA-2017-112004 | B6: First Class | C6: Adam Hart | D6: Corporate | E6: Pennsylvania | F6: 19013 | G6: Laptop | H6: 6.0165 | I6: 8.595 | J6: 5 | K6: =I6*J6 -> 42.975 | L6: =J6*(I6-H6) -> 12.8925 | M6: =L6/K6 -> 0.3
A7: US-2017-147655 | B7: First Class | C7: Aaron Smayling | D7: Corporate | E7: Oregon | F7: 97756 | G7: Laptop | H7: 61.6518 | I7: 88.074 | J7: 7 | K7: =I7*J7 -> 616.518 | L7: =J7*(I7-H7) -> 184.9554 | M7: =L7/K7 -> 0.3
A8: US-2014-158400 | B8: First Class | C8: Aaron Hawkins | D8: Corporate | E8: California | F8: 94109 | G8: Laptop | H8: 34.5856 | I8: 49.408 | J8: 4 | K8: =I8*J8 -> 197.632 | L8: =J8*(I8-H8) -> 59.2896 | M8: =L8/K8 -> 0.3
A9: CA-2016-145261 | B9: First Class | C9: Adrian Hane | D9: Home Office | E9: Oregon | F9: 97301 | G9: Laptop | H9: 31.668 | I9: 45.24 | J9: 4 | K9: =I9*J9 -> 180.96 | L9: =J9*(I9-H9) -> 54.288 | M9: =L9/K9 -> 0.3
A10: CA-2017-118213 | B10: First Class | C10: Adam Bellavance | D10: Home Office | E10: Indiana | F10: 46142 | G10: Laptop | H10: 3.087 | I10: 4.41 | J10: 1 | K10: =I10*J10 -> 4.41 | L10: =J10*(I10-H10) -> 1.323 | M10: =L10/K10 -> 0.3
A11: CA-2017-126788 | B11: First Class | C11: Adrian Barton | D11: Consumer | E11: Texas | F11: 77581 | G11: Mobile | H11: 329.2632 | I11: 470.376 | J11: 3 | K11: =I11*J11 -> 1411.128 | L11: =J11*(I11-H11) -> 423.3384 | M11: =L11/K11 -> 0.3
A12: CA-2017-136448 | B12: First Class | C12: Adam Shillingsburg | D12: Consumer | E12: Pennsylvania | F12: 19143 | G12: Mobile | H12: 50.3832 | I12: 71.976 | J12: 3 | K12: =I12*J12 -> 215.928 | L12: =J12*(I12-H12) -> 64.7784 | M12: =L12/K12 -> 0.3
A13: CA-2017-121643 | B13: First Class | C13: Adrian Barton | D13: Consumer | E13: Oregon | F13: 97206 | G13: Mobile | H13: 241.2928 | I13: 344.704 | J13: 2 | K13: =I13*J13 -> 689.408 | L13: =J13*(I13-H13) -> 206.8224 | M13: =L13/K13 -> 0.3
... A60: US-2016-108637 | B60: Standard Class | C60: Adam Bellavance | D60: Home Office | E60: Virginia | F60: 22980 | G60: TV | H60: 89.516 | I60: 127.88 | J60: 2 | K60: =I60*J60 -> 255.76 | L60: =J60*(I60-H60) -> 76.728 | M60: =L60/K60 -> 0.3

Sheet Formulas
M1: VLOOKUP | N1: XLOOKUP | O1: Profit Status (USING IF) | P1: Sales Category(USING IFS) | Q1: CATEGORY | R1: SUMIFS | S1: COUNTIFS
M2: =VLOOKUP(Raw_data!A2,SalesData[],7,) -> Laptop | N2: Virginia | O2: {=IF(SalesData[Profit]>200,"High Profit","Low Profit")} -> Low Profit | P2: {=_xlfn.IFS(SalesData[Sales]>1100,"High",SalesData[Sales]>800,"Medium",TRUE,"Low")} -> Low | Q2: Laptop | R2: =SUMIFS(SalesData[Sales],SalesData[Category],Raw_data!G4) -> 138997.06 | S2: =COUNTIFS(SalesData[Category],SalesData[[#This Row],[Category]]) -> 34
N3: Laptop | O3: Low Profit | P3: Low | Q3: TV | R3: =SUMIFS(SalesData[Sales],SalesData[Category],Raw_data!G18) -> 28641.495 | S3: =COUNTIFS(SalesData[Category],Raw_data!G18) -> 14
O4: Low Profit | P4: Low | Q4: Mobile | R4: =SUMIFS(SalesData[Sales],SalesData[Category],Raw_data!G13) -> 9133.148 | S4: =COUNTIFS(SalesData[Category],Raw_data!G15) -> 11
N5: {=_xlfn.XLOOKUP(Formulas!N2&Formulas!N3,Raw_data!E:E&Raw_data!G:G,Raw_data!I:I,1)} -> 34.65 | O5: Low Profit | P5: Low
O6: Low Profit | P6: Low
H7: Formula | I7: Meaning | J7: Syntax | K7: Use case | O7: Low Profit | P7: Low
H8: VLOOKUP | I8: Find data vertically | J8: =VLOOKUP() | K8: Find category from Order ID | O8: Low Profit | P8: Low
H9: XLOOKUP | I9: Modern lookup | J9: =XLOOKUP() | K9: Better VLOOKUP | O9: Low Profit | P9: Low
H10: IF | I10: Decision making | J10: =IF() | K10: High Profit and Low Profit | O10: Low Profit | P10: Low
H11: IFS | I11: Multiple decisions | J11: =IFS() | K11: High/Medium/Low sales | O11: High Profit | P11: High
H12: SUMIFS | I12: Conditional sum | J12: =SUMIFS() | K12: Sales by category | O12: Low Profit | P12: Low
H13: COUNTIFS | I13: Conditional count | J13: =COUNTIFS() | K13: Orders by category | O13: High Profit | P13: Low
O14: Low Profit | P14: Low
O15: High Profit | P15: High
O16: Low Profit | P16: Low
O17: Low Profit | P17: Low
O18: Low Profit | P18: Low
O19: High Profit | P19: Medium
O20: High Profit | P20: Medium
O21: High Profit | P21: Medium
O22: Low Profit | P22: Low
O23: High Profit | P23: Medium
O24: Low Profit | P24: Low
O25: Low Profit | P25: Low
... O60: Low Profit | P60: Low

Sheet Analysis
A3: Row Labels | B3: Total Sales | C3: Total Profit | D3: Total Quantity | F3: Row Labels | G3: Total Sales | H3: Total Profit | I3: Total Quantity
A4: Laptop | B4: 138997.06 | C4: 41699.119 | D4: 135 | F4: Washington | G4: 14343.812 | H4: 4303.1436 | I4: 10
A5: TV | B5: 28641.495 | C5: 8592.4485 | D5: 56 | F5: Virginia | G5: 422.51 | H5: 126.753 | I5: 7
A6: Mobile | B6: 9133.148 | C6: 2739.9444 | D6: 30 | F6: Texas | G6: 6402.45 | H6: 1920.735 | I6: 24
A7: Grand Total | B7: 176771.71 | C7: 53031.512 | D7: 221 | F7: Tennessee | G7: 943.056 | H7: 282.9168 | I7: 3
F8: Rhode Island | G8: 962.976 | H8: 288.8928 | I8: 4
F9: Pennsylvania | G9: 472.775 | H9: 141.8325 | I9: 19
F10: Oregon | G10: 1486.886 | H10: 446.0658 | I10: 13
F11: Oklahoma | G11: 443.96 | H11: 133.188 | I11: 2
A12: Row Labels | B12: Total Profit | C12: Total Sales | D12: Total Quantity | F12: Ohio | G12: 6.016 | H12: 1.8048 | I12: 2
A13: Consumer | B13: 41785.414 | C13: 139284.71 | D13: 72 | F13: North Carolina | G13: 1391.4 | H13: 417.42 | I13: 2
A14: Corporate | B14: 5873.4975 | C14: 19578.325 | D14: 105 | F14: New York | G14: 5211.576 | H14: 1563.4728 | I14: 35
A15: Home Office | B15: 5372.6004 | C15: 17908.668 | D15: 44 | F15: New Hampshire | G15: 83.79 | H15: 25.137 | I15: 3
A16: Grand Total | B16: 53031.512 | C16: 176771.71 | D16: 221 | F16: Nevada | G16: 982.25 | H16: 294.675 | I16: 5
F17: Missouri | G17: 616.86 | H17: 185.058 | I17: 9
F18: Mississippi | G18: 605.15 | H18: 181.545 | I18: 7
F19: Michigan | G19: 128605.62 | H19: 38581.686 | I19: 13
F20: Kentucky | G20: 5240.07 | H20: 1572.021 | I20: 9
F21: Indiana | G21: 8.1 | H21: 2.43 | I21: 2
F22: Illinois | G22: 482.288 | H22: 144.6864 | I22: 12
F23: Georgia | G23: 38.52 | H23: 11.556 | I23: 3
F24: California | G24: 5780.354 | H24: 1734.1062 | I24: 28
F25: Arizona | G25: 2241.287 | H25: 672.3861 | I25: 9
F26: Grand Total | G26: 176771.71 | H26: 53031.512 | I26: 221

Sheet Dashboard
I2: Total Sales | K2: Total Profits | M2: Total Orders | O2: Total Quantity
I3: =SUM(SalesData[Sales]) -> 176771.71 | K3: =SUM(SalesData[Profit]) -> 53031.512 | M3: =COUNTA(SalesData[Order ID]) -> 59 | O3: =SUM(SalesData[Quantity]) -> 221
